CHANGELOG.txt
COPYING
MANIFEST.in
README.txt
TODO.txt
ez_setup.py
setup.py
clipboard_modifier.egg-info/PKG-INFO
clipboard_modifier.egg-info/SOURCES.txt
clipboard_modifier.egg-info/dependency_links.txt
clipboard_modifier.egg-info/top_level.txt
clipboardmodifier/__init__.py
clipboardmodifier/clipboardmodifier.py
clipboardmodifier/plugins/__init__.py
clipboardmodifier/plugins/_plugin.py
clipboardmodifier/plugins/amazonlink.py
clipboardmodifier/plugins/colstocommasep.py
clipboardmodifier/plugins/donothing.py
clipboardmodifier/plugins/fixnumbers.py
clipboardmodifier/plugins/forcetotext.py
clipboardmodifier/plugins/i18n.py
clipboardmodifier/plugins/linestocols.py
clipboardmodifier/plugins/rot13.py
clipboardmodifier/plugins/runapp.py
clipboardmodifier/plugins/searchreplace.py
clipboardmodifier/plugins/show_python_var.py
clipboardmodifier/plugins/tabtobars.py
clipboardmodifier/plugins/text2unicode.py
clipboardmodifier/plugins/tojava.py
clipboardmodifier/plugins/url2python.py
clipboardmodifier/plugins/urltotext.py
doc/sample-sort-shot.png
doc/show_python-shot.png
man/clipboard-modifier.1
scripts/clipboard-modifier