Metadata-Version: 1.0
Name: clipboard-modifier
Version: 0.2.1
Summary: Change your clipboard text in a variety of ways.
Home-page: http://code.google.com/p/clipboard-modifier/
Author: Scott Kirkwood
Author-email: scott@forusers.com
License: Apache 2.0
Download-URL: http://clipboard-modifier.googlecode.com/files/clipboard-modifier-0.2.1.zip
Keywords: clipboard,utility,wxPython,Python
Platform: POSIX
Platform: Windows
Classifier: Development Status :: 2 - Pre-Alpha
Classifier: Environment :: Console
Classifier: Intended Audience :: Developers
Classifier: Intended Audience :: Information Technology
Classifier: License :: OSI Approved :: Apache Software License
Classifier: Operating System :: OS Independent
Classifier: Operating System :: Microsoft :: Windows
Classifier: Operating System :: POSIX
Classifier: Programming Language :: Python
Classifier: Topic :: Utilities
